setup.cfg
setup.py
wire_mafia.egg-info/PKG-INFO
wire_mafia.egg-info/SOURCES.txt
wire_mafia.egg-info/dependency_links.txt
wire_mafia.egg-info/entry_points.txt
wire_mafia.egg-info/requires.txt
wire_mafia.egg-info/top_level.txt
wiremafia/__init__.py
wiremafia/ansi.py
wiremafia/blocker.py
wiremafia/cli.py