Metadata-Version: 1.0
Name: wire-mafia
Version: 0.0.1
Summary: Block select applications from the wifi. Like the mafia.
Home-page: https://github.com/kepoorhampond/blockade
Author: Kepoor Hampond
Author-email: kepoorh@gmail.com
License: MIT
Platform: UNKNOWN
